rule34Python/__init__.py
rule34Python/req.py
rule34Python/reqRe.py
rule34Python/rule34.py
rule34Python/test.py
rule34Python/yandereRe.py
rule34Python-0.0.1.4.dist-info/METADATA
rule34Python-0.0.1.4.dist-info/WHEEL
rule34Python-0.0.1.4.dist-info/top_level.txt
rule34Python-0.0.1.4.dist-info/RECORD
