Metadata-Version: 2.1
Name: rule34Python
Version: 0.0.1.4
Summary: rule 34 api public, get post 
Home-page: https://github.com/EverGasterXd/sara_api
Author: evergaster
License: MIT license
Keywords: nsfw rule rule34
Classifier: License :: OSI Approved :: MIT License
Classifier: Operating System :: OS Independent
Classifier: Development Status :: 4 - Beta
Classifier: Natural Language :: English
Classifier: Operating System :: Microsoft :: Windows :: Windows 10
Classifier: Programming Language :: Python :: 3
Classifier: Programming Language :: Python :: 3.9
Classifier: Topic :: Internet
Requires-Python: >=3.0
Requires-Dist: requests
